vbaf/__init__.py
vbaf/fuzzers.py
vbaf-1.0.0.dist-info/licenses/LICENSE
vbaf-1.0.0.dist-info/METADATA
vbaf-1.0.0.dist-info/WHEEL
vbaf-1.0.0.dist-info/top_level.txt
vbaf-1.0.0.dist-info/RECORD
