Metadata-Version: 2.4
Name: vbaf
Version: 1.0.0
Summary: Vocabulary-Based Adversarial Fuzzing (VB-AF) framework for Large Language Models (LLMs)
Author-email: Ameya Srivastava <srivastava.ameya@gmail.com>
License: Apache-2.0
Project-URL: Homepage, https://0ameyasr.github.io/VB-AF/
Project-URL: Repository, https://github.com/0ameyasr/VB-AF
Project-URL: Documentation, https://0ameyasr.github.io/VB-AF/
Project-URL: Issues, https://github.com/0ameyasr/VB-AF/issues
Requires-Python: >=3.8
License-File: LICENSE
Dynamic: license-file
